{"ts": "2026-07-24T14:44:47-04:00", "provider": "alpaca-iex", "window_min": 15, "rows": [{"ticker": "HYLB", "last": 36.155, "day_pct": 0.0003, "pace": 2.2924, "tp": 10.1529, "vs_vwap": -0.0002, "dollar_w": 1126921.58, "dshare": 0.0557, "state": "NEW MONEY", "note": "quiet open (0.5x) \u2192 now 10.2x \u00b7 taking +5.6% flow share", "peak_tp": 13.5735, "surge": 5.6717}, {"ticker": "AXP", "last": 323.09, "day_pct": -0.052, "pace": 2.4098, "tp": 2.2774, "vs_vwap": 0.0021, "dollar_w": 2673751.46, "dshare": -0.0812, "state": "CHURN", "note": "2.3x participation, no progress at highs \u2014 absorption", "peak_tp": 3.1386, "surge": 1.2052}, {"ticker": "BBIN", "last": 77.69, "day_pct": 0.004, "pace": 19.2753, "tp": 43.9003, "vs_vwap": -0.0023, "dollar_w": 77690.0, "dshare": -0.0285, "state": "FADING", "note": "pace 43.9x vs peak 178.6x \u00b7 -0.6% off HOD \u00b7 chart still +0% \u2014 crowd buying a cooled tape", "peak_tp": 178.6485, "surge": 24.6121}, {"ticker": "BAB", "last": 26.395, "day_pct": 0.0028, "pace": 2.4931, "tp": 27.8587, "vs_vwap": -0.0002, "dollar_w": 100301.0, "dshare": 0.0095, "state": "NEW MONEY", "note": "quiet open (0.2x) \u2192 now 27.9x \u00b7 taking +1.0% flow share", "peak_tp": 27.8587, "surge": 15.6006}, {"ticker": "CHRW", "last": 192.135, "day_pct": -0.0651, "pace": 3.0409, "tp": 1.8312, "vs_vwap": 0.0082, "dollar_w": 876442.405, "dshare": -0.03, "state": "RUNNING", "note": "sustained 1.8x", "peak_tp": 9.8085, "surge": 0.9571}, {"ticker": "ATCL", "last": 24.595, "day_pct": 0.0014, "pace": 6.1216, "tp": 28.1753, "vs_vwap": -0.0, "dollar_w": 49190.0, "dshare": 0.0048, "state": "CHURN", "note": "28.2x participation, no progress at highs \u2014 absorption", "peak_tp": 30.984, "surge": 15.7555}, {"ticker": "BCS", "last": 27.955, "day_pct": 0.0107, "pace": 1.9009, "tp": 2.1283, "vs_vwap": 0.002, "dollar_w": 373938.185, "dshare": 0.0423, "state": "FADING", "note": "pace 2.1x vs peak 8.1x \u00b7 -0.6% off HOD \u00b7 chart still +1% \u2014 crowd buying a cooled tape", "peak_tp": 8.1226, "surge": 1.2022}, {"ticker": "FSBC", "last": 46.92, "day_pct": -0.0073, "pace": 0.7832, "tp": 6.8441, "vs_vwap": -0.0056, "dollar_w": 91211.68, "dshare": 0.0104, "state": "IGNITING", "note": "pace 6.8x and accelerating (4.1x vs prior window) \u00b7 -0.5% in window", "peak_tp": 6.8441, "surge": 3.8075}, {"ticker": "AAOX", "last": 12.595, "day_pct": -0.2118, "pace": 1.4227, "tp": 4.8863, "vs_vwap": -0.0496, "dollar_w": 87495.64, "dshare": 0.0038, "state": "RUNNING", "note": "sustained 4.9x", "peak_tp": 4.8863, "surge": 2.1611}, {"ticker": "CHTR", "last": 124.7, "day_pct": -0.0144, "pace": 2.3076, "tp": 0.7414, "vs_vwap": 0.028, "dollar_w": 373696.385, "dshare": 0.0133, "state": "COOLING", "note": "pace 0.7x off peak 3.7x", "peak_tp": 3.6835, "surge": 0.4051}, {"ticker": "ASTL", "last": 4.41, "day_pct": 0.015, "pace": 1.714, "tp": 6.5026, "vs_vwap": 0.0035, "dollar_w": 42140.455, "dshare": 0.0009, "state": "RUNNING", "note": "sustained 6.5x", "peak_tp": 9.2945, "surge": 3.7062}, {"ticker": "AIPO", "last": 29.31, "day_pct": -0.0374, "pace": 3.3683, "tp": 2.5642, "vs_vwap": -0.0164, "dollar_w": 84472.18, "dshare": 0.0004, "state": "RUNNING", "note": "sustained 2.6x", "peak_tp": 17.4887, "surge": 1.3783}, {"ticker": "CDXS", "last": 1.515, "day_pct": -0.2368, "pace": 9.5586, "tp": 9.3259, "vs_vwap": 0.0049, "dollar_w": 20254.925, "dshare": 0.0016, "state": "IGNITING", "note": "pace 9.3x and accelerating (2.0x vs prior window) \u00b7 -1.3% in window", "peak_tp": 33.5784, "surge": 3.9845}, {"ticker": "EVH", "last": 4.275, "day_pct": -0.0747, "pace": 1.9222, "tp": 3.6718, "vs_vwap": -0.0332, "dollar_w": 47789.055, "dshare": 0.004, "state": "NEW MONEY", "note": "quiet open (0.9x) \u2192 now 3.7x \u00b7 taking +0.4% flow share", "peak_tp": 5.8599, "surge": 1.8948}, {"ticker": "ABCB", "last": 87.06, "day_pct": -0.0225, "pace": 2.8625, "tp": 1.7812, "vs_vwap": 0.0002, "dollar_w": 92750.64, "dshare": 0.0027, "state": "COOLING", "note": "pace 1.8x off peak 4.9x", "peak_tp": 4.8699, "surge": 0.9735}, {"ticker": "BAH", "last": 73.9, "day_pct": 0.1228, "pace": 1.3757, "tp": 0.6738, "vs_vwap": 0.0073, "dollar_w": 192739.295, "dshare": 0.005, "state": "FADING", "note": "pace 0.7x vs peak 4.5x \u00b7 -2.7% off HOD \u00b7 chart still +12% \u2014 crowd buying a cooled tape", "peak_tp": 4.5, "surge": 0.4218}, {"ticker": "NTGR", "last": 24.96, "day_pct": -0.0048, "pace": 1.09, "tp": 2.6535, "vs_vwap": -0.0138, "dollar_w": 41992.115, "dshare": 0.0024, "state": "NEW MONEY", "note": "quiet open (0.3x) \u2192 now 2.7x \u00b7 taking +0.2% flow share", "peak_tp": 3.3539, "surge": 1.4855}, {"ticker": "BBCQ", "last": 10.23, "day_pct": -0.0029, "pace": 10.2798, "tp": 12.3007, "vs_vwap": -0.0, "dollar_w": 7774.8, "dshare": -0.0006, "state": "CHURN", "note": "12.3x participation, no progress at highs \u2014 absorption", "peak_tp": 28.4402, "surge": 6.8486}, {"ticker": "UVSP", "last": 44.5, "day_pct": 0.0075, "pace": 1.1316, "tp": 2.3072, "vs_vwap": -0.0039, "dollar_w": 40679.36, "dshare": -0.0, "state": "RUNNING", "note": "sustained 2.3x", "peak_tp": 5.419, "surge": 1.2982}, {"ticker": "BDN", "last": 3.18, "day_pct": 0.0358, "pace": 0.9087, "tp": 3.009, "vs_vwap": 0.0004, "dollar_w": 28153.32, "dshare": 0.0028, "state": "NEW MONEY", "note": "quiet open (0.8x) \u2192 now 3.0x \u00b7 taking +0.3% flow share", "peak_tp": 6.3928, "surge": 1.7427}, {"ticker": "NVCR", "last": 18.44, "day_pct": -0.0771, "pace": 2.3926, "tp": 0.9649, "vs_vwap": -0.0206, "dollar_w": 40502.09, "dshare": -0.017, "state": "COOLING", "note": "pace 1.0x off peak 5.3x", "peak_tp": 5.3012, "surge": 0.4978}, {"ticker": "NBBK", "last": 22.28, "day_pct": -0.0002, "pace": 3.3256, "tp": 1.3257, "vs_vwap": -0.0057, "dollar_w": 26536.29, "dshare": 0.0012, "state": "COOLING", "note": "pace 1.3x off peak 10.9x", "peak_tp": 10.8789, "surge": 0.7414}, {"ticker": "AIN", "last": 75.66, "day_pct": 0.015, "pace": 0.134, "tp": 1.119, "vs_vwap": -0.0015, "dollar_w": 25875.72, "dshare": 0.0038, "state": "QUIET", "note": "", "peak_tp": 1.4396, "surge": 0.6342}, {"ticker": "HTH", "last": 39.84, "day_pct": 0.0531, "pace": 0.748, "tp": 1.4665, "vs_vwap": -0.0024, "dollar_w": 16610.53, "dshare": -0.0017, "state": "COOLING", "note": "pace 1.5x off peak 2.9x", "peak_tp": 2.8834, "surge": 0.8622}, {"ticker": "BELFA", "last": 233.71, "day_pct": -0.0329, "pace": 0.6789, "tp": 0.9315, "vs_vwap": -0.0047, "dollar_w": 23371.0, "dshare": 0.0034, "state": "COOLING", "note": "pace 0.9x off peak 3.2x", "peak_tp": 3.1898, "surge": 0.503}, {"ticker": "BNTX", "last": 89.69, "day_pct": -0.0262, "pace": 3.1439, "tp": 0.4446, "vs_vwap": -0.0041, "dollar_w": 45659.91, "dshare": 0.0056, "state": "COOLING", "note": "pace 0.4x off peak 19.6x", "peak_tp": 19.5682, "surge": 0.2418}, {"ticker": "SFL", "last": 11.955, "day_pct": 0.008, "pace": 0.8289, "tp": 0.9121, "vs_vwap": 0.0023, "dollar_w": 21528.485, "dshare": 0.0028, "state": "FADING", "note": "pace 0.9x vs peak 3.1x \u00b7 -0.6% off HOD \u00b7 chart still +1% \u2014 crowd buying a cooled tape", "peak_tp": 3.1325, "surge": 0.5128}, {"ticker": "PZZA", "last": 30.96, "day_pct": 0.0204, "pace": 0.6144, "tp": 0.779, "vs_vwap": 0.0057, "dollar_w": 24112.56, "dshare": 0.0015, "state": "QUIET", "note": "", "peak_tp": 1.6419, "surge": 0.4444}, {"ticker": "HYLS", "last": 40.42, "day_pct": 0.0006, "pace": 0.9536, "tp": 1.0111, "vs_vwap": -0.0001, "dollar_w": 16168.0, "dshare": 0.0024, "state": "FADING", "note": "pace 1.0x vs peak 10.6x \u00b7 -0.1% off HOD \u00b7 chart still +0% \u2014 crowd buying a cooled tape", "peak_tp": 10.6199, "surge": 0.5649}, {"ticker": "MSBI", "last": 32.3, "day_pct": 0.0419, "pace": 0.7426, "tp": 1.2989, "vs_vwap": 0.0097, "dollar_w": 12403.2, "dshare": -0.0008, "state": "FADING", "note": "pace 1.3x vs peak 3.1x \u00b7 chart still +4%", "peak_tp": 3.1276, "surge": 0.7557}, {"ticker": "WOOF", "last": 2.6, "day_pct": 0.0236, "pace": 0.845, "tp": 1.453, "vs_vwap": -0.0024, "dollar_w": 8293.52, "dshare": -0.0006, "state": "LEAVING", "note": "pace 1.5x off peak 2.6x \u00b7 VWAP lost (was +1.7% above)", "peak_tp": 2.6494, "surge": 0.831}, {"ticker": "CAC", "last": 54.8, "day_pct": 0.0233, "pace": 0.4581, "tp": 1.3999, "vs_vwap": 0.0013, "dollar_w": 8220.0, "dshare": 0.0012, "state": "FADING", "note": "pace 1.4x vs peak 2.8x \u00b7 chart still +2%", "peak_tp": 2.7853, "surge": 0.8}, {"ticker": "CHT", "last": 42.87, "day_pct": 0.0112, "pace": 0.4787, "tp": 1.1276, "vs_vwap": 0.0014, "dollar_w": 9131.31, "dshare": 0.0013, "state": "COOLING", "note": "pace 1.1x off peak 1.9x", "peak_tp": 1.9048, "surge": 0.6367}, {"ticker": "ACNB", "last": 62.88, "day_pct": 0.0003, "pace": 2.2279, "tp": 1.4642, "vs_vwap": 0.0038, "dollar_w": 6350.88, "dshare": 0.0009, "state": "FADING", "note": "pace 1.5x vs peak 8.4x \u00b7 -0.8% off HOD \u00b7 chart still +0% \u2014 crowd buying a cooled tape", "peak_tp": 8.4267, "surge": 0.8179}, {"ticker": "DOMO", "last": 3.685, "day_pct": -0.0671, "pace": 2.5823, "tp": 0.8733, "vs_vwap": -0.0237, "dollar_w": 9242.55, "dshare": 0.0005, "state": "LEAVING", "note": "still out \u2014 pace 0.9x vs peak 18.1x", "peak_tp": 18.0633, "surge": 0.4537}, {"ticker": "AERO", "last": 14.95, "day_pct": 0.0034, "pace": 0.8183, "tp": 1.0563, "vs_vwap": -0.0155, "dollar_w": 7477.5, "dshare": 0.0005, "state": "FADING", "note": "pace 1.1x vs peak 6.0x \u00b7 -2.5% off HOD \u00b7 chart still +0% \u2014 crowd buying a cooled tape", "peak_tp": 6.0239, "surge": 0.592}, {"ticker": "ADVB", "last": 20.16, "day_pct": 0.2021, "pace": 0.9644, "tp": 0.917, "vs_vwap": 0.0387, "dollar_w": 7721.28, "dshare": 0.0009, "state": "FADING", "note": "pace 0.9x vs peak 4.0x \u00b7 -12.3% off HOD \u00b7 chart still +20% \u2014 crowd buying a cooled tape", "peak_tp": 3.9814, "surge": 0.6155}, {"ticker": "BCAL", "last": 20.99, "day_pct": 0.0118, "pace": 0.4516, "tp": 1.0925, "vs_vwap": -0.0014, "dollar_w": 6128.06, "dshare": 0.0004, "state": "QUIET", "note": "", "peak_tp": 1.4726, "surge": 0.6172}, {"ticker": "CBRG", "last": 4.18, "day_pct": -0.2068, "pace": 1.0334, "tp": 0.846, "vs_vwap": -0.0286, "dollar_w": 7073.0, "dshare": 0.0007, "state": "LEAVING", "note": "still out \u2014 pace 0.8x vs peak 4.1x", "peak_tp": 4.0915, "surge": 0.373}, {"ticker": "DBO", "last": 22.54, "day_pct": -0.0276, "pace": 2.1284, "tp": 0.8269, "vs_vwap": 0.0017, "dollar_w": 6765.0, "dshare": 0.001, "state": "COOLING", "note": "pace 0.8x off peak 10.8x", "peak_tp": 10.8299, "surge": 0.4492}, {"ticker": "AWP", "last": 12.22, "day_pct": 0.0116, "pace": 2.3032, "tp": 1.2814, "vs_vwap": -0.0024, "dollar_w": 3971.5, "dshare": 0.0004, "state": "FADING", "note": "pace 1.3x vs peak 4.8x \u00b7 -0.5% off HOD \u00b7 chart still +1% \u2014 crowd buying a cooled tape", "peak_tp": 4.7574, "surge": 0.7238}, {"ticker": "TSLZ", "last": 17.77, "day_pct": 0.0789, "pace": 1.1989, "tp": 0.3854, "vs_vwap": 0.0275, "dollar_w": 12822.59, "dshare": -0.0052, "state": "FADING", "note": "pace 0.4x vs peak 4.5x \u00b7 -0.1% off HOD \u00b7 chart still +8% \u2014 crowd buying a cooled tape", "peak_tp": 4.4637, "surge": 0.2324}, {"ticker": "CHIQ", "last": 17.295, "day_pct": -0.0111, "pace": 45.5887, "tp": 2.0732, "vs_vwap": -0.0027, "dollar_w": 2334.825, "dshare": -0.0044, "state": "RUNNING", "note": "sustained 2.1x", "peak_tp": 80.1596, "surge": 1.1448}, {"ticker": "BNRG", "last": 0.7049, "day_pct": -0.1304, "pace": 10.3812, "tp": 4.3304, "vs_vwap": -0.0831, "dollar_w": 976.33, "dshare": 0.0, "state": "RUNNING", "note": "sustained 4.3x", "peak_tp": 36.4566, "surge": 2.0804}, {"ticker": "BLFS", "last": 30.145, "day_pct": -0.0219, "pace": 0.8249, "tp": 0.1494, "vs_vwap": -0.0013, "dollar_w": 12641.5, "dshare": -0.0021, "state": "COOLING", "note": "pace 0.1x off peak 3.2x", "peak_tp": 3.1979, "surge": 0.0817}, {"ticker": "SSL", "last": 11.825, "day_pct": -0.0179, "pace": 0.3605, "tp": 0.3228, "vs_vwap": 0.0005, "dollar_w": 10149.405, "dshare": 0.0004, "state": "QUIET", "note": "", "peak_tp": 1.5845, "surge": 0.1771}, {"ticker": "ALOT", "last": 28.78, "day_pct": 0.0028, "pace": 0.452, "tp": 0.9397, "vs_vwap": 0.0004, "dollar_w": 2878.0, "dshare": 0.0001, "state": "FADING", "note": "pace 0.9x vs peak 4.6x \u00b7 -0.1% off HOD \u00b7 chart still +0% \u2014 crowd buying a cooled tape", "peak_tp": 4.6169, "surge": 0.5262}, {"ticker": "CGIC", "last": 35.48, "day_pct": -0.0008, "pace": 1.4913, "tp": 0.3423, "vs_vwap": -0.0019, "dollar_w": 7096.0, "dshare": 0.001, "state": "COOLING", "note": "pace 0.3x off peak 9.1x", "peak_tp": 9.0518, "surge": 0.191}, {"ticker": "BFLX", "last": 25.245, "day_pct": 0.0012, "pace": 0.7533, "tp": 0.9493, "vs_vwap": -0.0044, "dollar_w": 2524.5, "dshare": 0.0004, "state": "FADING", "note": "pace 0.9x vs peak 7.0x \u00b7 -0.6% off HOD \u00b7 chart still +0% \u2014 crowd buying a cooled tape", "peak_tp": 6.994, "surge": 0.5307}, {"ticker": "BWX", "last": 21.38, "day_pct": 0.0007, "pace": 3.0616, "tp": 0.3721, "vs_vwap": 0.0007, "dollar_w": 4276.0, "dshare": 0.0006, "state": "FADING", "note": "pace 0.4x vs peak 5.2x \u00b7 -0.2% off HOD \u00b7 chart still +0% \u2014 crowd buying a cooled tape", "peak_tp": 5.2104, "surge": 0.2079}, {"ticker": "CGBD", "last": 10.015, "day_pct": -0.0005, "pace": 0.3957, "tp": 0.3465, "vs_vwap": -0.001, "dollar_w": 4474.97, "dshare": -0.0004, "state": "QUIET", "note": "", "peak_tp": 1.3822, "surge": 0.1933}, {"ticker": "BTCI", "last": 28.37, "day_pct": -0.0079, "pace": 1.476, "tp": 0.4893, "vs_vwap": 0.0023, "dollar_w": 2865.37, "dshare": -0.0006, "state": "QUIET", "note": "", "peak_tp": 1.5781, "surge": 0.2711}, {"ticker": "THRM", "last": 43.975, "day_pct": -0.0367, "pace": 1.7621, "tp": 0.174, "vs_vwap": -0.0409, "dollar_w": 4397.5, "dshare": 0.0006, "state": "LEAVING", "note": "pace 0.2x off peak 6.3x \u00b7 VWAP lost (was +1.7% above)", "peak_tp": 6.2804, "surge": 0.0936}, {"ticker": "VNM", "last": 16.485, "day_pct": -0.0129, "pace": 0.561, "tp": 0.3645, "vs_vwap": -0.0036, "dollar_w": 3297.5, "dshare": 0.0001, "state": "COOLING", "note": "pace 0.4x off peak 5.3x", "peak_tp": 5.2726, "surge": 0.201}, {"ticker": "KRNY", "last": 9.435, "day_pct": 0.0345, "pace": 0.8075, "tp": 0.2399, "vs_vwap": 0.0079, "dollar_w": 3668.715, "dshare": -0.0002, "state": "FADING", "note": "pace 0.2x vs peak 4.3x \u00b7 -0.1% off HOD \u00b7 chart still +3% \u2014 crowd buying a cooled tape", "peak_tp": 4.312, "surge": 0.1385}, {"ticker": "IKT", "last": 2.38, "day_pct": 0.0193, "pace": 1.8463, "tp": 0.3134, "vs_vwap": -0.0239, "dollar_w": 1719.98, "dshare": 0.0001, "state": "LEAVING", "note": "pace 0.3x off peak 4.9x \u00b7 VWAP lost (was +4.0% above)", "peak_tp": 4.9254, "surge": 0.1788}, {"ticker": "ELPC", "last": 11.445, "day_pct": -0.0243, "pace": 0.651, "tp": 0.1872, "vs_vwap": -0.0103, "dollar_w": 1144.5, "dshare": -0.0004, "state": "COOLING", "note": "pace 0.2x off peak 3.5x", "peak_tp": 3.5159, "surge": 0.102}, {"ticker": "ACIO", "last": 45.81, "day_pct": 0.0033, "pace": 0.5711, "tp": 0.0, "vs_vwap": -0.0019, "dollar_w": 0.0, "dshare": -0.0006, "state": "FADING", "note": "pace 0.0x vs peak 8.8x \u00b7 -0.3% off HOD \u00b7 chart still +0% \u2014 crowd buying a cooled tape", "peak_tp": 8.7766, "surge": 0.0}, {"ticker": "ADX", "last": 25.92, "day_pct": 0.0, "pace": 0.8289, "tp": 0.0, "vs_vwap": -0.0034, "dollar_w": 0.0, "dshare": -0.0003, "state": "COOLING", "note": "pace 0.0x off peak 6.0x", "peak_tp": 5.9692, "surge": 0.0}, {"ticker": "ASGI", "last": 24.49, "day_pct": -0.0049, "pace": 1.598, "tp": 0.0, "vs_vwap": -0.0064, "dollar_w": 0.0, "dshare": 0.0, "state": "COOLING", "note": "pace 0.0x off peak 2.1x", "peak_tp": 2.1127, "surge": 0.0}, {"ticker": "ATLO", "last": 30.21, "day_pct": 0.0151, "pace": 0.3236, "tp": 0.0, "vs_vwap": -0.0021, "dollar_w": 0.0, "dshare": 0.0, "state": "QUIET", "note": "", "peak_tp": 1.4742, "surge": 0.0}, {"ticker": "AVIV", "last": 79.355, "day_pct": 0.0094, "pace": 0.0903, "tp": 0.0, "vs_vwap": 0.0011, "dollar_w": 0.0, "dshare": 0.0, "state": "QUIET", "note": "", "peak_tp": 1.1181, "surge": 0.0}, {"ticker": "BSJU", "last": 25.525, "day_pct": 0.0, "pace": 2.3837, "tp": 0.0, "vs_vwap": 0.0004, "dollar_w": 0.0, "dshare": 0.0, "state": "COOLING", "note": "pace 0.0x off peak 22.5x", "peak_tp": 22.4809, "surge": 0.0}, {"ticker": "BGSI", "last": 102.67, "day_pct": 0.0133, "pace": 0.1794, "tp": 0.0, "vs_vwap": -0.0001, "dollar_w": 0.0, "dshare": 0.0, "state": "FADING", "note": "pace 0.0x vs peak 2.2x \u00b7 -0.0% off HOD \u00b7 chart still +1% \u2014 crowd buying a cooled tape", "peak_tp": 2.2179, "surge": 0.0}, {"ticker": "BSCR", "last": 19.575, "day_pct": 0.0, "pace": 1.8025, "tp": 0.0, "vs_vwap": 0.0, "dollar_w": 0.0, "dshare": 0.0, "state": "COOLING", "note": "pace 0.0x off peak 9.1x", "peak_tp": 9.1278, "surge": 0.0}, {"ticker": "CALI", "last": 50.33, "day_pct": 0.0002, "pace": 0.5623, "tp": 0.0, "vs_vwap": -0.0001, "dollar_w": 0.0, "dshare": -0.0012, "state": "FADING", "note": "pace 0.0x vs peak 5.5x \u00b7 -0.0% off HOD \u00b7 chart still +0% \u2014 crowd buying a cooled tape", "peak_tp": 5.4518, "surge": 0.0}, {"ticker": "HCSG", "last": 22.66, "day_pct": 0.0105, "pace": 1.841, "tp": 0.0, "vs_vwap": -0.0034, "dollar_w": 0.0, "dshare": -0.003, "state": "FADING", "note": "pace 0.0x vs peak 8.5x \u00b7 -1.8% off HOD \u00b7 chart still +1% \u2014 crowd buying a cooled tape", "peak_tp": 8.5069, "surge": 0.0}, {"ticker": "BBSI", "last": 39.87, "day_pct": 0.0025, "pace": 0.112, "tp": 0.0, "vs_vwap": 0.0031, "dollar_w": 0.0, "dshare": -0.001, "state": "QUIET", "note": "", "peak_tp": 0.6399, "surge": 0.0}, {"ticker": "CHMG", "last": 79.47, "day_pct": 0.0683, "pace": 1.1105, "tp": 0.0, "vs_vwap": 0.0032, "dollar_w": 0.0, "dshare": 0.0, "state": "QUIET", "note": "", "peak_tp": 1.4677, "surge": 0.0}, {"ticker": "BOW", "last": 30.705, "day_pct": 0.0398, "pace": 0.2362, "tp": 0.0, "vs_vwap": 0.0014, "dollar_w": 0.0, "dshare": 0.0, "state": "FADING", "note": "pace 0.0x vs peak 2.1x \u00b7 +0.0% off HOD \u00b7 chart still +4% \u2014 crowd buying a cooled tape", "peak_tp": 2.1482, "surge": 0.0}, {"ticker": "AFK", "last": 25.57, "day_pct": 0.0091, "pace": 13.2917, "tp": 0.0, "vs_vwap": 0.0076, "dollar_w": 0.0, "dshare": 0.0, "state": "FADING", "note": "pace 0.0x vs peak 143.7x \u00b7 +0.0% off HOD \u00b7 chart still +1% \u2014 crowd buying a cooled tape", "peak_tp": 143.7047, "surge": 0.0}, {"ticker": "CCB", "last": 72.96, "day_pct": 0.0203, "pace": 1.1582, "tp": 0.0, "vs_vwap": -0.0016, "dollar_w": 0.0, "dshare": 0.0, "state": "FADING", "note": "pace 0.0x vs peak 14.4x \u00b7 -0.5% off HOD \u00b7 chart still +2% \u2014 crowd buying a cooled tape", "peak_tp": 14.4397, "surge": 0.0}, {"ticker": "LEMB", "last": 42.155, "day_pct": 0.0049, "pace": 1.9497, "tp": 0.0, "vs_vwap": 0.0014, "dollar_w": 0.0, "dshare": 0.0, "state": "FADING", "note": "pace 0.0x vs peak 11.8x \u00b7 -0.0% off HOD \u00b7 chart still +0% \u2014 crowd buying a cooled tape", "peak_tp": 11.8411, "surge": 0.0}, {"ticker": "ASR", "last": 268.49, "day_pct": -0.0047, "pace": 1.3436, "tp": 0.0, "vs_vwap": 0.0181, "dollar_w": 0.0, "dshare": -0.0042, "state": "COOLING", "note": "pace 0.0x off peak 2.1x", "peak_tp": 2.113, "surge": 0.0}, {"ticker": "CBRZ", "last": 16.03, "day_pct": 0.1963, "pace": 7.2233, "tp": 0.0, "vs_vwap": 0.0265, "dollar_w": 0.0, "dshare": -0.0022, "state": "FADING", "note": "pace 0.0x vs peak 25.0x \u00b7 -2.8% off HOD \u00b7 chart still +20% \u2014 crowd buying a cooled tape", "peak_tp": 25.0474, "surge": 0.0}, {"ticker": "BILZ", "last": 100.875, "day_pct": 0.0002, "pace": 14.9386, "tp": 0.0, "vs_vwap": 0.0, "dollar_w": 0.0, "dshare": 0.0, "state": "FADING", "note": "pace 0.0x vs peak 124.1x \u00b7 +0.0% off HOD \u00b7 chart still +0% \u2014 crowd buying a cooled tape", "peak_tp": 124.1216, "surge": 0.0}, {"ticker": "BKTI", "last": 78.27, "day_pct": 0.0128, "pace": 0.0823, "tp": 0.0, "vs_vwap": 0.0, "dollar_w": 0.0, "dshare": 0.0, "state": "FADING", "note": "pace 0.0x vs peak 2.4x \u00b7 +0.0% off HOD \u00b7 chart still +1% \u2014 crowd buying a cooled tape", "peak_tp": 2.3813, "surge": 0.0}, {"ticker": "APOS", "last": 25.8, "day_pct": 0.0031, "pace": 10.3907, "tp": 0.0, "vs_vwap": 0.0003, "dollar_w": 0.0, "dshare": 0.0, "state": "QUIET", "note": "", "peak_tp": 0.0, "surge": 0.0}, {"ticker": "BEDY", "last": 29.41, "day_pct": 0.0148, "pace": 0.1746, "tp": 0.0, "vs_vwap": 0.0014, "dollar_w": 0.0, "dshare": 0.0, "state": "QUIET", "note": "", "peak_tp": 0.7503, "surge": 0.0}, {"ticker": "ITM", "last": 45.945, "day_pct": 0.0021, "pace": 0.3856, "tp": 0.0, "vs_vwap": -0.0001, "dollar_w": 0.0, "dshare": -0.0042, "state": "FADING", "note": "pace 0.0x vs peak 7.1x \u00b7 -0.1% off HOD \u00b7 chart still +0% \u2014 crowd buying a cooled tape", "peak_tp": 7.139, "surge": 0.0}, {"ticker": "BMNP", "last": 86.64, "day_pct": -0.005, "pace": 0.169, "tp": 0.0, "vs_vwap": 0.0, "dollar_w": 0.0, "dshare": 0.0, "state": "COOLING", "note": "pace 0.0x off peak 3.8x", "peak_tp": 3.766, "surge": 0.0}, {"ticker": "NEA", "last": 11.26, "day_pct": 0.0031, "pace": 0.4401, "tp": 0.0, "vs_vwap": 0.0003, "dollar_w": 0.0, "dshare": 0.0, "state": "FADING", "note": "pace 0.0x vs peak 2.0x \u00b7 -0.1% off HOD \u00b7 chart still +0% \u2014 crowd buying a cooled tape", "peak_tp": 2.0452, "surge": 0.0}, {"ticker": "ACOG", "last": 7.915, "day_pct": -0.0288, "pace": 0.4346, "tp": 0.0, "vs_vwap": -0.026, "dollar_w": 0.0, "dshare": 0.0, "state": "COOLING", "note": "pace 0.0x off peak 4.7x", "peak_tp": 4.7045, "surge": 0.0}, {"ticker": "CCIX", "last": 10.875, "day_pct": 0.0005, "pace": 4.1207, "tp": 0.0, "vs_vwap": 0.0005, "dollar_w": 0.0, "dshare": 0.0, "state": "FADING", "note": "pace 0.0x vs peak 23.8x \u00b7 +0.0% off HOD \u00b7 chart still +0% \u2014 crowd buying a cooled tape", "peak_tp": 23.7536, "surge": 0.0}, {"ticker": "AVLC", "last": 88.835, "day_pct": 0.0003, "pace": 0.5577, "tp": 0.0, "vs_vwap": -0.0005, "dollar_w": 0.0, "dshare": -0.0011, "state": "FADING", "note": "pace 0.0x vs peak 6.7x \u00b7 -0.1% off HOD \u00b7 chart still +0% \u2014 crowd buying a cooled tape", "peak_tp": 6.6769, "surge": 0.0}, {"ticker": "BUFZ", "last": 27.985, "day_pct": 0.0045, "pace": 0.1303, "tp": 0.0, "vs_vwap": 0.0004, "dollar_w": 0.0, "dshare": 0.0, "state": "FADING", "note": "pace 0.0x vs peak 2.8x \u00b7 +0.0% off HOD \u00b7 chart still +0% \u2014 crowd buying a cooled tape", "peak_tp": 2.8088, "surge": 0.0}], "rot_in": [{"ticker": "ATCL", "surge": 15.76}, {"ticker": "BAB", "surge": 15.6}, {"ticker": "FSBC", "surge": 3.81}, {"ticker": "HYLB", "surge": 5.67}], "rot_out": [{"ticker": "ACIO", "frac": 0.0}, {"ticker": "ADX", "frac": 0.0}, {"ticker": "ASGI", "frac": 0.0}, {"ticker": "BSJU", "frac": 0.0}]}