{"v": 4, "ts": "2026-07-22T12:03:30-04:00", "rows": [{"ticker": "ZCMD", "day_pct": 5.1224, "last": 9.0, "pace": 16.64, "dollar_day": 2214585.0, "promoted": true}, {"ticker": "LABT", "day_pct": 0.8944, "last": 3.41, "pace": 909.47, "dollar_day": 770209.88, "promoted": true}, {"ticker": "ADVB", "day_pct": 0.6691, "last": 11.35, "pace": 21.95, "dollar_day": 695959.2999999999, "promoted": true}, {"ticker": "SMCZ", "day_pct": -0.4982, "last": 5.59, "pace": 174.7, "dollar_day": 460481.83999999997, "promoted": true}, {"ticker": "SMCX", "day_pct": 0.4907, "last": 9.645, "pace": 5.5, "dollar_day": 597768.1649999999, "promoted": true}, {"ticker": "SMCL", "day_pct": 0.4792, "last": 13.18, "pace": 2.35, "dollar_day": 123628.4, "promoted": true}, {"ticker": "ZBAO", "day_pct": 0.4717, "last": 0.262, "pace": 42.75, "dollar_day": 231784.74240000002, "promoted": true}, {"ticker": "KSCP", "day_pct": 0.4685, "last": 2.1, "pace": 13.35, "dollar_day": 285457.2, "promoted": true}, {"ticker": "OTLY", "day_pct": 0.3194, "last": 11.98, "pace": 6.97, "dollar_day": 148096.76, "promoted": true}, {"ticker": "RBKB", "day_pct": -0.3189, "last": 11.95, "pace": 168.87, "dollar_day": 341853.64999999997, "promoted": true}, {"ticker": "AGPU", "day_pct": -0.2879, "last": 6.79, "pace": 9.3, "dollar_day": 120312.01, "promoted": true}, {"ticker": "KUST", "day_pct": 0.2476, "last": 1.285, "pace": 12.59, "dollar_day": 376111.79, "promoted": true}, {"ticker": "SMCI", "day_pct": 0.247, "last": 31.785, "pace": 5.15, "dollar_day": 110556494.1, "promoted": true}, {"ticker": "QTEX", "day_pct": -0.2418, "last": 0.887, "pace": 4.45, "dollar_day": 109790.1573, "promoted": true}, {"ticker": "ARWR", "day_pct": 0.2332, "last": 91.85, "pace": 3.3, "dollar_day": 14809618.45, "promoted": true}]}