{"v": 4, "ts": "2026-07-22T09:07:59-04:00", "session": "pre", "rows": [{"headline": null, "pr_ts": null, "catalyst": false, "flags": null, "ticker": "LABT", "move": 2.2611, "last": 5.87, "dollars": 456717.25, "vs_adv": 124.68, "off_hi": -0.1543, "state": null, "tp": null, "hot": false, "pin": false, "heat": 99.2, "swings": 9, "path": 3.008, "first_seen": "08:24", "new": false}, {"headline": null, "pr_ts": null, "catalyst": false, "flags": null, "ticker": "INM", "move": 0.4733, "last": 2.21, "dollars": 148904.76000000004, "vs_adv": 37.94, "off_hi": -0.225, "state": null, "tp": null, "hot": false, "pin": false, "heat": 90.1, "swings": 3, "path": 1.225, "first_seen": "08:43", "new": false}]}