{"v": 4, "ts": "2026-07-24T10:57:21-04:00", "session": "rth", "rows": [{"headline": null, "pr_ts": null, "catalyst": false, "flags": null, "ticker": "VIVK", "move": 0.366, "last": 2.855, "dollars": 835165.38, "vs_adv": 7.04, "off_hi": -0.2015, "state": null, "open": 3.595, "ssr": false, "vs_vwap": null, "tp": null, "hot": false, "pin": false, "heat": 99.2, "swings": 4, "path": 2.515, "first_seen": "08:16", "new": false}, {"headline": null, "pr_ts": null, "catalyst": false, "flags": null, "ticker": "GSUN", "move": 0.2488, "last": 0.43, "dollars": 96526.153, "vs_adv": 6.85, "off_hi": -0.2056, "state": null, "open": 0.3815, "ssr": false, "vs_vwap": null, "tp": null, "hot": false, "pin": false, "heat": 96.5, "swings": 4, "path": 1.769, "first_seen": "10:21", "new": false}, {"headline": null, "pr_ts": null, "catalyst": false, "flags": null, "ticker": "LVWR", "move": 0.6937, "last": 1.43, "dollars": 863073.69, "vs_adv": 64.34, "off_hi": -0.1402, "state": null, "open": 1.26, "ssr": false, "vs_vwap": null, "tp": null, "hot": false, "pin": false, "heat": 96.2, "swings": 5, "path": 1.705, "first_seen": "09:36", "new": false}, {"headline": null, "pr_ts": null, "catalyst": false, "flags": null, "ticker": "WLDS", "move": 0.204, "last": 2.685, "dollars": 110739.48, "vs_adv": 5.29, "off_hi": -0.1154, "state": null, "open": 2.595, "ssr": false, "vs_vwap": null, "tp": null, "hot": false, "pin": false, "heat": 92.5, "swings": 4, "path": 1.368, "first_seen": "10:21", "new": false}, {"headline": null, "pr_ts": null, "catalyst": false, "flags": null, "ticker": "CBRG", "move": -0.2334, "last": 4.04, "dollars": 123539.16, "vs_adv": 0.4, "off_hi": -0.1847, "state": "COOLING", "open": 4.95, "ssr": true, "vs_vwap": -0.05408314870144837, "tp": null, "hot": false, "pin": false, "heat": 60.6, "swings": 0, "path": 0.515, "first_seen": "10:06", "new": false}, {"headline": null, "pr_ts": null, "catalyst": false, "flags": null, "ticker": "NEBX", "move": -0.224, "last": 25.49, "dollars": 206927.18000000002, "vs_adv": 0.38, "off_hi": -0.2187, "state": null, "open": 31.92, "ssr": true, "vs_vwap": null, "tp": null, "hot": false, "pin": false, "heat": 51.9, "swings": 0, "path": 0.436, "first_seen": "10:40", "new": false}, {"headline": null, "pr_ts": null, "catalyst": false, "flags": null, "ticker": "CDXS", "move": -0.2519, "last": 1.485, "dollars": 270932.31, "vs_adv": 3.32, "off_hi": -0.0511, "state": "LEAVING", "open": 1.465, "ssr": true, "vs_vwap": -0.010680384730724302, "tp": null, "hot": false, "pin": false, "heat": 48.5, "swings": 0, "path": 0.554, "first_seen": "09:36", "new": false}, {"headline": null, "pr_ts": null, "catalyst": false, "flags": null, "ticker": "LODE", "move": -0.2162, "last": 3.045, "dollars": 182887.02, "vs_adv": 0.9, "off_hi": -0.1331, "state": null, "open": 3.53, "ssr": true, "vs_vwap": null, "tp": null, "hot": false, "pin": false, "heat": 46.1, "swings": 0, "path": 0.471, "first_seen": "09:43", "new": false}, {"headline": null, "pr_ts": null, "catalyst": false, "flags": null, "ticker": "NBIL", "move": -0.2312, "last": 24.54, "dollars": 177473.28, "vs_adv": 0.37, "off_hi": -0.1573, "state": null, "open": 28.77, "ssr": true, "vs_vwap": null, "tp": null, "hot": false, "pin": false, "heat": 45.4, "swings": 0, "path": 0.35, "first_seen": "09:47", "new": false}, {"headline": null, "pr_ts": null, "catalyst": false, "flags": null, "ticker": "ZVRA", "move": -0.2132, "last": 9.835, "dollars": 1290905.935, "vs_adv": 1.86, "off_hi": -0.0339, "state": null, "open": 9.25, "ssr": true, "vs_vwap": null, "tp": null, "hot": false, "pin": false, "heat": 33.2, "swings": 0, "path": 0.345, "first_seen": "09:36", "new": false}, {"headline": null, "pr_ts": null, "catalyst": false, "flags": null, "ticker": "RNG", "move": 0.233, "last": 47.57, "dollars": 4473524.95, "vs_adv": 0.92, "off_hi": -0.0279, "state": null, "open": 40.49, "ssr": false, "vs_vwap": null, "tp": null, "hot": false, "pin": false, "heat": 30.9, "swings": 0, "path": 0.448, "first_seen": "09:36", "new": false}, {"headline": null, "pr_ts": null, "catalyst": false, "flags": null, "ticker": "NBIZ", "move": 0.2264, "last": 27.03, "dollars": 387934.56, "vs_adv": 0.88, "off_hi": -0.0103, "state": null, "open": 23.35, "ssr": false, "vs_vwap": null, "tp": null, "hot": false, "pin": false, "heat": 27.4, "swings": 0, "path": 0.266, "first_seen": "09:40", "new": false}, {"headline": null, "pr_ts": null, "catalyst": false, "flags": null, "ticker": "NBIG", "move": -0.235, "last": 16.73, "dollars": 126796.67, "vs_adv": 0.46, "off_hi": -0.1791, "state": null, "open": 20.38, "ssr": true, "vs_vwap": null, "tp": null, "hot": false, "pin": false, "heat": 22.4, "swings": 0, "path": 0.285, "first_seen": "10:21", "new": false}, {"headline": null, "pr_ts": null, "catalyst": false, "flags": null, "ticker": "CBRZ", "move": 0.2201, "last": 16.35, "dollars": 144141.6, "vs_adv": 3.9, "off_hi": -0.0085, "state": "CHURN", "open": 14.0, "ssr": false, "vs_vwap": 0.048186416173275015, "tp": null, "hot": true, "pin": false, "heat": 19.1, "swings": 0, "path": 0.233, "first_seen": "09:55", "new": false}, {"headline": null, "pr_ts": null, "catalyst": false, "flags": null, "ticker": "SAFT", "move": 0.4164, "last": 103.07, "dollars": 2312787.73, "vs_adv": 4.71, "off_hi": -0.0031, "state": null, "open": 103.19, "ssr": false, "vs_vwap": null, "tp": null, "hot": false, "pin": true, "heat": 0.0, "swings": 0, "path": 0.0, "first_seen": "09:32", "new": false}]}