{"v": 4, "ts": "2026-07-23T10:21:47-04:00", "rows": [{"ticker": "WBUY", "pace": 22812.8, "last": 1.14, "day_pct": 0.7978, "dollar_day": 3241625.34, "promoted": true}, {"ticker": "WLDS", "pace": 364.69, "last": 1.85, "day_pct": 0.3214, "dollar_day": 34313.8, "promoted": false}, {"ticker": "SPXD", "pace": 395.54, "last": 28.65, "day_pct": 0.0, "dollar_day": 14353.65, "promoted": false}, {"ticker": "ETS", "pace": 213.79, "last": 1.01, "day_pct": 0.1265, "dollar_day": 14758.12, "promoted": false}, {"ticker": "JENA", "pace": 117.07, "last": 10.4, "day_pct": 0.0, "dollar_day": 431028.0, "promoted": true}, {"ticker": "BUFM", "pace": 126.45, "last": 40.42, "day_pct": -0.0044, "dollar_day": 145512.0, "promoted": false}, {"ticker": "TOK", "pace": 117.64, "last": 150.21, "day_pct": 0.0, "dollar_day": 305226.72000000003, "promoted": true}, {"ticker": "AUGZ", "pace": 117.64, "last": 45.5, "day_pct": 0.0, "dollar_day": 220629.5, "promoted": true}, {"ticker": "MAGX", "pace": 110.91, "last": 49.34, "day_pct": -0.0898, "dollar_day": 411890.32, "promoted": true}, {"ticker": "SSEA", "pace": 116.47, "last": 10.27, "day_pct": 0.0, "dollar_day": 205400.0, "promoted": true}, {"ticker": "APXT", "pace": 108.82, "last": 10.14, "day_pct": 0.0, "dollar_day": 401878.62, "promoted": true}, {"ticker": "GCGRW", "pace": 181.63, "last": 0.74, "day_pct": -0.1084, "dollar_day": 1856.66, "promoted": false}, {"ticker": "APRZ", "pace": 117.64, "last": 39.92, "day_pct": 0.0, "dollar_day": 100079.44, "promoted": false}, {"ticker": "JUNZ", "pace": 117.64, "last": 35.26, "day_pct": 0.0, "dollar_day": 91676.0, "promoted": false}, {"ticker": "MHY", "pace": 112.12, "last": 25.65, "day_pct": 0.0, "dollar_day": 153900.0, "promoted": true}, {"ticker": "MIGO", "pace": 103.81, "last": 29.17, "day_pct": 0.0, "dollar_day": 306605.87, "promoted": true}]}