{"v": 4, "ts": "2026-07-22T13:12:34-04:00", "rows": [{"ticker": "ZCMD", "day_pct": 2.8095, "last": 5.6, "pace": 15.2, "dollar_day": 1673560.0, "promoted": true}, {"ticker": "ADVB", "day_pct": 1.2721, "last": 15.45, "pace": 23.24, "dollar_day": 1333953.0, "promoted": true}, {"ticker": "LABT", "day_pct": 0.7722, "last": 3.19, "pace": 729.19, "dollar_day": 768311.5, "promoted": true}, {"ticker": "ZBAO", "day_pct": 0.5294, "last": 0.273, "pace": 65.46, "dollar_day": 490483.674, "promoted": true}, {"ticker": "KSCP", "day_pct": 0.5245, "last": 2.18, "pace": 13.96, "dollar_day": 412161.7, "promoted": true}, {"ticker": "SMCL", "day_pct": 0.4736, "last": 13.13, "pace": 1.99, "dollar_day": 138521.5, "promoted": true}, {"ticker": "SMCZ", "day_pct": -0.4686, "last": 5.92, "pace": 153.03, "dollar_day": 568106.88, "promoted": true}, {"ticker": "SMCX", "day_pct": 0.459, "last": 9.44, "pace": 5.39, "dollar_day": 763658.24, "promoted": true}, {"ticker": "RBKB", "day_pct": -0.3166, "last": 11.99, "pace": 129.64, "dollar_day": 350191.93, "promoted": true}, {"ticker": "OTLY", "day_pct": 0.2924, "last": 11.735, "pace": 7.78, "dollar_day": 215454.59999999998, "promoted": true}, {"ticker": "AGPU", "day_pct": -0.269, "last": 6.97, "pace": 9.7, "dollar_day": 171245.93, "promoted": true}, {"ticker": "KUST", "day_pct": 0.2573, "last": 1.295, "pace": 9.64, "dollar_day": 386017.485, "promoted": true}, {"ticker": "AIRJ", "day_pct": 0.2467, "last": 4.7, "pace": 2.14, "dollar_day": 274639.8, "promoted": true}, {"ticker": "QTEX", "day_pct": -0.2412, "last": 0.888, "pace": 4.84, "dollar_day": 158848.7272, "promoted": true}, {"ticker": "SMCI", "day_pct": 0.2297, "last": 31.345, "pace": 4.45, "dollar_day": 125493531.58999999, "promoted": true}]}