{"v": 4, "ts": "2026-07-22T11:55:32-04:00", "session": "rth", "rows": [{"headline": null, "pr_ts": null, "catalyst": false, "flags": null, "ticker": "ZCMD", "move": 4.5374, "last": 8.14, "dollars": 1990732.98, "vs_adv": 6.51, "off_hi": -0.281, "state": null, "open": 2.28, "ssr": false, "vs_vwap": null, "tp": null, "hot": false, "pin": true, "heat": 100.0, "swings": 11, "path": 4.976, "first_seen": "09:16", "new": false}, {"headline": null, "pr_ts": null, "catalyst": false, "flags": null, "ticker": "LABT", "move": 0.85, "last": 3.33, "dollars": 745367.22, "vs_adv": 363.4, "off_hi": -0.5124, "state": "FADING", "open": 6.45, "ssr": false, "vs_vwap": -0.22091828650013656, "tp": null, "hot": true, "pin": false, "heat": 100.0, "swings": 19, "path": 5.696, "first_seen": "08:24", "new": false}, {"headline": null, "pr_ts": null, "catalyst": false, "flags": null, "ticker": "ZBAO", "move": 0.5698, "last": 0.28, "dollars": 216228.14919999999, "vs_adv": 15.97, "off_hi": -0.3632, "state": null, "open": 0.1686, "ssr": true, "vs_vwap": null, "tp": null, "hot": false, "pin": false, "heat": 99.3, "swings": 6, "path": 2.651, "first_seen": "11:35", "new": false}, {"headline": null, "pr_ts": null, "catalyst": false, "flags": null, "ticker": "KUST", "move": 0.2233, "last": 1.26, "dollars": 360086.25, "vs_adv": 4.99, "off_hi": -0.3243, "state": null, "open": 1.15, "ssr": false, "vs_vwap": null, "tp": null, "hot": false, "pin": false, "heat": 99.0, "swings": 5, "path": 2.388, "first_seen": "10:43", "new": false}, {"headline": null, "pr_ts": null, "catalyst": false, "flags": null, "ticker": "ADVB", "move": 0.7279, "last": 11.75, "dollars": 622614.78, "vs_adv": 8.1, "off_hi": -0.1534, "state": "LEAVING", "open": 10.42, "ssr": false, "vs_vwap": 0.02011428349330946, "tp": null, "hot": true, "pin": false, "heat": 98.9, "swings": 10, "path": 2.58, "first_seen": "10:43", "new": false}, {"headline": null, "pr_ts": null, "catalyst": false, "flags": null, "ticker": "KSCP", "move": 0.4825, "last": 2.12, "dollars": 272317.5, "vs_adv": 5.14, "off_hi": -0.0278, "state": null, "open": 1.485, "ssr": false, "vs_vwap": null, "tp": null, "hot": false, "pin": false, "heat": 88.9, "swings": 0, "path": 1.167, "first_seen": "10:43", "new": false}, {"headline": null, "pr_ts": null, "catalyst": false, "flags": null, "ticker": "QTEX", "move": -0.2236, "last": 0.908, "dollars": 109831.9188, "vs_adv": 1.75, "off_hi": -0.0778, "state": null, "open": 0.985, "ssr": true, "vs_vwap": null, "tp": null, "hot": false, "pin": false, "heat": 54.6, "swings": 1, "path": 0.735, "first_seen": "10:50", "new": false}, {"headline": null, "pr_ts": null, "catalyst": false, "flags": null, "ticker": "SMCZ", "move": -0.4883, "last": 5.7, "dollars": 419212.2, "vs_adv": 62.89, "off_hi": -0.2105, "state": null, "open": 7.22, "ssr": true, "vs_vwap": null, "tp": null, "hot": false, "pin": false, "heat": 42.9, "swings": 2, "path": 0.635, "first_seen": "10:43", "new": false}, {"headline": null, "pr_ts": null, "catalyst": false, "flags": null, "ticker": "OTLY", "move": 0.3381, "last": 12.15, "dollars": 111439.8, "vs_adv": 2.09, "off_hi": -0.021, "state": null, "open": 10.5, "ssr": false, "vs_vwap": null, "tp": null, "hot": false, "pin": false, "heat": 36.9, "swings": 0, "path": 0.308, "first_seen": "11:21", "new": false}, {"headline": null, "pr_ts": null, "catalyst": false, "flags": null, "ticker": "SMCX", "move": 0.4784, "last": 9.565, "dollars": 581322.44, "vs_adv": 2.17, "off_hi": -0.0149, "state": null, "open": 8.34, "ssr": false, "vs_vwap": null, "tp": null, "hot": false, "pin": false, "heat": 22.4, "swings": 0, "path": 0.537, "first_seen": "09:36", "new": false}, {"headline": null, "pr_ts": null, "catalyst": false, "flags": null, "ticker": "AGPU", "move": -0.291, "last": 6.76, "dollars": 117769.2, "vs_adv": 3.67, "off_hi": -0.2184, "state": "RUNNING", "open": 8.7, "ssr": true, "vs_vwap": -0.04985348566416403, "tp": null, "hot": true, "pin": false, "heat": 19.6, "swings": 2, "path": 0.488, "first_seen": "10:47", "new": false}, {"headline": null, "pr_ts": null, "catalyst": false, "flags": null, "ticker": "ARWR", "move": 0.2291, "last": 91.54, "dollars": 14329873.8, "vs_adv": 1.3, "off_hi": -0.0445, "state": "FADING", "open": 85.46, "ssr": false, "vs_vwap": 0.006658473410192434, "tp": null, "hot": false, "pin": false, "heat": 9.2, "swings": 0, "path": 0.272, "first_seen": "09:32", "new": false}, {"headline": null, "pr_ts": null, "catalyst": false, "flags": null, "ticker": "SMCL", "move": 0.4792, "last": 13.18, "dollars": 123628.4, "vs_adv": 0.95, "off_hi": -0.009, "state": null, "open": 11.69, "ssr": false, "vs_vwap": null, "tp": null, "hot": false, "pin": false, "heat": 6.9, "swings": 0, "path": 0.37, "first_seen": "10:43", "new": false}, {"headline": null, "pr_ts": null, "catalyst": false, "flags": null, "ticker": "SMCI", "move": 0.2444, "last": 31.72, "dollars": 108066702.8, "vs_adv": 2.03, "off_hi": -0.0078, "state": null, "open": 28.98, "ssr": false, "vs_vwap": null, "tp": null, "hot": false, "pin": false, "heat": 5.5, "swings": 0, "path": 0.273, "first_seen": "09:36", "new": false}, {"headline": null, "pr_ts": null, "catalyst": false, "flags": null, "ticker": "RBKB", "move": -0.3189, "last": 11.95, "dollars": 330405.55, "vs_adv": 65.81, "off_hi": -0.0157, "state": null, "open": 11.74, "ssr": true, "vs_vwap": null, "tp": null, "hot": false, "pin": true, "heat": 0.2, "swings": 0, "path": 0.041, "first_seen": "10:43", "new": false}]}