{"ts": "2026-07-24T12:32:36-04:00", "provider": "alpaca-iex", "window_min": 15, "rows": [{"ticker": "AXP", "last": 323.7, "day_pct": -0.0502, "pace": 2.6239, "tp": 2.2617, "vs_vwap": 0.0053, "dollar_w": 2805665.61, "dshare": 0.1523, "state": "RUNNING", "note": "sustained 2.3x", "peak_tp": 2.5502, "surge": 1.2683}, {"ticker": "CHRW", "last": 189.06, "day_pct": -0.0801, "pace": 3.0405, "tp": 3.0065, "vs_vwap": -0.0059, "dollar_w": 1492909.695, "dshare": -0.163, "state": "RUNNING", "note": "sustained 3.0x", "peak_tp": 9.8085, "surge": 1.635}, {"ticker": "CHTR", "last": 119.66, "day_pct": -0.0542, "pace": 3.0066, "tp": 2.4501, "vs_vwap": -0.0115, "dollar_w": 1255349.78, "dshare": 0.0262, "state": "RUNNING", "note": "sustained 2.5x", "peak_tp": 3.6835, "surge": 1.3646}, {"ticker": "CHIQ", "last": 17.37, "day_pct": -0.0069, "pace": 37.4178, "tp": 35.2318, "vs_vwap": 0.0008, "dollar_w": 42051.47, "dshare": 0.0015, "state": "RUNNING", "note": "sustained 35.2x", "peak_tp": 62.9505, "surge": 20.6768}, {"ticker": "CLF", "last": 11.66, "day_pct": 0.0658, "pace": 3.0921, "tp": 2.1346, "vs_vwap": 0.0196, "dollar_w": 646991.165, "dshare": 0.0357, "state": "FADING", "note": "pace 2.1x vs peak 3.9x \u00b7 chart still +7%", "peak_tp": 3.8684, "surge": 1.3438}, {"ticker": "NBBK", "last": 22.44, "day_pct": 0.007, "pace": 4.0552, "tp": 4.5693, "vs_vwap": 0.0014, "dollar_w": 96952.885, "dshare": 0.0077, "state": "FADING", "note": "pace 4.6x vs peak 10.9x \u00b7 chart still +1%", "peak_tp": 10.8789, "surge": 2.7165}, {"ticker": "CDXS", "last": 1.5, "day_pct": -0.2443, "pace": 9.4482, "tp": 12.8094, "vs_vwap": -0.0016, "dollar_w": 29228.24, "dshare": 0.0023, "state": "LEAVING", "note": "pace 12.8x off peak 33.6x \u00b7 VWAP lost (was +3.2% above)", "peak_tp": 33.5784, "surge": 5.7662}, {"ticker": "CCB", "last": 73.155, "day_pct": 0.023, "pace": 1.6027, "tp": 5.6516, "vs_vwap": 0.001, "dollar_w": 55025.41, "dshare": 0.0075, "state": "NEW MONEY", "note": "quiet open (0.4x) \u2192 now 5.7x \u00b7 taking +0.8% flow share", "peak_tp": 14.4397, "surge": 3.4146}, {"ticker": "BAH", "last": 73.64, "day_pct": 0.1188, "pace": 1.577, "tp": 0.8355, "vs_vwap": 0.0024, "dollar_w": 251552.795, "dshare": -0.0038, "state": "FADING", "note": "pace 0.8x vs peak 4.5x \u00b7 -3.0% off HOD \u00b7 chart still +12% \u2014 crowd buying a cooled tape", "peak_tp": 4.5, "surge": 0.5521}, {"ticker": "AIPO", "last": 29.935, "day_pct": -0.0169, "pace": 4.2828, "tp": 2.3914, "vs_vwap": 0.0037, "dollar_w": 85097.595, "dshare": -0.0013, "state": "RUNNING", "note": "sustained 2.4x", "peak_tp": 17.4887, "surge": 1.3924}, {"ticker": "NVCR", "last": 18.305, "day_pct": -0.0838, "pace": 2.305, "tp": 1.3973, "vs_vwap": -0.0339, "dollar_w": 61278.875, "dshare": -0.0101, "state": "COOLING", "note": "pace 1.4x off peak 5.3x", "peak_tp": 5.3012, "surge": 0.7554}, {"ticker": "DBO", "last": 22.39, "day_pct": -0.0341, "pace": 2.6867, "tp": 2.9329, "vs_vwap": -0.0056, "dollar_w": 25108.36, "dshare": 0.003, "state": "NEW MONEY", "note": "quiet open (0.9x) \u2192 now 2.9x \u00b7 taking +0.3% flow share", "peak_tp": 10.8299, "surge": 1.6719}, {"ticker": "PZZA", "last": 31.125, "day_pct": 0.0259, "pace": 0.5803, "tp": 1.2089, "vs_vwap": 0.0154, "dollar_w": 39617.37, "dshare": 0.0024, "state": "QUIET", "note": "", "peak_tp": 1.53, "surge": 0.7322}, {"ticker": "AIN", "last": 75.77, "day_pct": 0.0164, "pace": 0.082, "tp": 1.3653, "vs_vwap": 0.0, "dollar_w": 33338.8, "dshare": 0.0046, "state": "QUIET", "note": "", "peak_tp": 1.4321, "surge": 0.8194}, {"ticker": "BCS", "last": 28.095, "day_pct": 0.0157, "pace": 2.4295, "tp": 0.4924, "vs_vwap": 0.0077, "dollar_w": 91627.425, "dshare": -0.005, "state": "FADING", "note": "pace 0.5x vs peak 8.1x \u00b7 -0.1% off HOD \u00b7 chart still +2% \u2014 crowd buying a cooled tape", "peak_tp": 8.1226, "surge": 0.2954}, {"ticker": "CAC", "last": 54.89, "day_pct": 0.025, "pace": 0.4726, "tp": 2.6554, "vs_vwap": 0.0049, "dollar_w": 16466.0, "dshare": 0.0022, "state": "NEW MONEY", "note": "quiet open (0.2x) \u2192 now 2.7x \u00b7 taking +0.2% flow share", "peak_tp": 2.7853, "surge": 1.6071}, {"ticker": "AAOX", "last": 13.51, "day_pct": -0.1546, "pace": 1.2616, "tp": 1.1731, "vs_vwap": 0.0038, "dollar_w": 23795.0, "dshare": 0.0004, "state": "COOLING", "note": "pace 1.2x off peak 2.5x", "peak_tp": 2.5405, "surge": 0.5894}, {"ticker": "BNTX", "last": 90.29, "day_pct": -0.0197, "pace": 4.5313, "tp": 0.4821, "vs_vwap": 0.0025, "dollar_w": 52515.45, "dshare": 0.0031, "state": "COOLING", "note": "pace 0.5x off peak 19.6x", "peak_tp": 19.5682, "surge": 0.2789}, {"ticker": "IKT", "last": 2.47, "day_pct": 0.0578, "pace": 2.4174, "tp": 1.9097, "vs_vwap": 0.0134, "dollar_w": 11402.54, "dshare": 0.0012, "state": "RUNNING", "note": "sustained 1.9x", "peak_tp": 4.9254, "surge": 1.1885}, {"ticker": "KRNY", "last": 9.43, "day_pct": 0.034, "pace": 0.9687, "tp": 0.823, "vs_vwap": 0.0093, "dollar_w": 13258.875, "dshare": 0.0013, "state": "FADING", "note": "pace 0.8x vs peak 4.3x \u00b7 +0.0% off HOD \u00b7 chart still +3% \u2014 crowd buying a cooled tape", "peak_tp": 4.312, "surge": 0.5021}, {"ticker": "ASTL", "last": 4.38, "day_pct": 0.0081, "pace": 1.443, "tp": 1.2539, "vs_vwap": 0.0054, "dollar_w": 8478.48, "dshare": 0.0005, "state": "FADING", "note": "pace 1.3x vs peak 5.3x \u00b7 -0.5% off HOD \u00b7 chart still +1% \u2014 crowd buying a cooled tape", "peak_tp": 5.2536, "surge": 0.7478}, {"ticker": "DOMO", "last": 3.74, "day_pct": -0.0532, "pace": 3.3988, "tp": 0.9379, "vs_vwap": -0.0118, "dollar_w": 10702.98, "dshare": -0.0207, "state": "COOLING", "note": "pace 0.9x off peak 18.1x", "peak_tp": 18.0633, "surge": 0.5269}, {"ticker": "ASGI", "last": 24.51, "day_pct": -0.0041, "pace": 2.2563, "tp": 1.2702, "vs_vwap": -0.006, "dollar_w": 7353.0, "dshare": 0.0007, "state": "COOLING", "note": "pace 1.3x off peak 2.1x", "peak_tp": 2.1127, "surge": 0.747}, {"ticker": "BWX", "last": 21.405, "day_pct": 0.0019, "pace": 4.4586, "tp": 0.8751, "vs_vwap": 0.0019, "dollar_w": 10617.88, "dshare": -0.0052, "state": "FADING", "note": "pace 0.9x vs peak 5.2x \u00b7 -0.1% off HOD \u00b7 chart still +0% \u2014 crowd buying a cooled tape", "peak_tp": 5.2104, "surge": 0.5177}, {"ticker": "HCSG", "last": 22.63, "day_pct": 0.0091, "pace": 2.4732, "tp": 0.5267, "vs_vwap": -0.0054, "dollar_w": 14734.22, "dshare": -0.0109, "state": "FADING", "note": "pace 0.5x vs peak 8.5x \u00b7 -1.9% off HOD \u00b7 chart still +1% \u2014 crowd buying a cooled tape", "peak_tp": 8.5069, "surge": 0.3134}, {"ticker": "BSJU", "last": 25.525, "day_pct": 0.0, "pace": 2.8845, "tp": 2.9502, "vs_vwap": 0.0005, "dollar_w": 2552.5, "dshare": 0.0003, "state": "NEW MONEY", "note": "quiet open (0.8x) \u2192 now 3.0x \u00b7 taking +0.0% flow share", "peak_tp": 22.4809, "surge": 1.742}, {"ticker": "BLFS", "last": 30.185, "day_pct": -0.0206, "pace": 0.8385, "tp": 0.2509, "vs_vwap": 0.0, "dollar_w": 22404.44, "dshare": -0.0034, "state": "COOLING", "note": "pace 0.3x off peak 3.2x", "peak_tp": 3.1979, "surge": 0.1452}, {"ticker": "CBRG", "last": 4.47, "day_pct": -0.1518, "pace": 1.3618, "tp": 0.8023, "vs_vwap": 0.0374, "dollar_w": 7638.0, "dshare": -0.0031, "state": "COOLING", "note": "pace 0.8x off peak 4.1x", "peak_tp": 4.0915, "surge": 0.4039}, {"ticker": "ABCB", "last": 87.38, "day_pct": -0.0189, "pace": 2.7905, "tp": 0.3255, "vs_vwap": 0.0051, "dollar_w": 17912.9, "dshare": -0.0083, "state": "COOLING", "note": "pace 0.3x off peak 4.9x", "peak_tp": 4.8699, "surge": 0.1886}, {"ticker": "SFL", "last": 11.88, "day_pct": 0.0017, "pace": 0.8762, "tp": 0.4851, "vs_vwap": -0.0043, "dollar_w": 12015.18, "dshare": -0.0021, "state": "FADING", "note": "pace 0.5x vs peak 3.1x \u00b7 -1.2% off HOD \u00b7 chart still +0% \u2014 crowd buying a cooled tape", "peak_tp": 3.1325, "surge": 0.287}, {"ticker": "CGIC", "last": 35.665, "day_pct": 0.0044, "pace": 2.0645, "tp": 0.487, "vs_vwap": 0.0034, "dollar_w": 10699.5, "dshare": 0.0015, "state": "FADING", "note": "pace 0.5x vs peak 9.1x \u00b7 -0.2% off HOD \u00b7 chart still +0% \u2014 crowd buying a cooled tape", "peak_tp": 9.0518, "surge": 0.2888}, {"ticker": "WOOF", "last": 2.63, "day_pct": 0.0354, "pace": 0.7146, "tp": 0.9177, "vs_vwap": 0.0086, "dollar_w": 5585.275, "dshare": 0.0005, "state": "FADING", "note": "pace 0.9x vs peak 2.3x \u00b7 chart still +4%", "peak_tp": 2.2905, "surge": 0.5612}, {"ticker": "THRM", "last": 44.67, "day_pct": -0.0215, "pace": 1.8343, "tp": 0.4208, "vs_vwap": -0.0413, "dollar_w": 11393.175, "dshare": -0.0033, "state": "LEAVING", "note": "pace 0.4x off peak 6.3x \u00b7 VWAP lost (was +1.7% above)", "peak_tp": 6.2804, "surge": 0.2432}, {"ticker": "BNRG", "last": 0.701, "day_pct": -0.1352, "pace": 12.4006, "tp": 4.4004, "vs_vwap": -0.1171, "dollar_w": 1050.51, "dshare": -0.0, "state": "RUNNING", "note": "sustained 4.4x", "peak_tp": 36.4566, "surge": 2.2448}, {"ticker": "TSLZ", "last": 17.47, "day_pct": 0.0607, "pace": 1.4509, "tp": 0.2687, "vs_vwap": 0.0147, "dollar_w": 9248.1, "dshare": -0.0014, "state": "FADING", "note": "pace 0.3x vs peak 4.5x \u00b7 -0.9% off HOD \u00b7 chart still +6% \u2014 crowd buying a cooled tape", "peak_tp": 4.4637, "surge": 0.1681}, {"ticker": "AERO", "last": 15.195, "day_pct": 0.0198, "pace": 0.8697, "tp": 0.6011, "vs_vwap": -0.0026, "dollar_w": 4566.0, "dshare": -0.0039, "state": "FADING", "note": "pace 0.6x vs peak 6.0x \u00b7 -0.9% off HOD \u00b7 chart still +2% \u2014 crowd buying a cooled tape", "peak_tp": 6.0239, "surge": 0.3626}, {"ticker": "SSL", "last": 11.8, "day_pct": -0.0199, "pace": 0.4679, "tp": 0.2276, "vs_vwap": -0.0017, "dollar_w": 7526.765, "dshare": 0.0009, "state": "QUIET", "note": "", "peak_tp": 1.5845, "surge": 0.1317}, {"ticker": "ELPC", "last": 11.545, "day_pct": -0.0158, "pace": 0.7892, "tp": 0.5325, "vs_vwap": -0.0038, "dollar_w": 3463.5, "dshare": -0.0005, "state": "COOLING", "note": "pace 0.5x off peak 3.5x", "peak_tp": 3.5159, "surge": 0.3095}, {"ticker": "EVH", "last": 4.39, "day_pct": -0.0498, "pace": 2.0032, "tp": 0.3497, "vs_vwap": -0.0195, "dollar_w": 4931.855, "dshare": -0.001, "state": "COOLING", "note": "pace 0.3x off peak 4.2x", "peak_tp": 4.1512, "surge": 0.1961}, {"ticker": "UVSP", "last": 44.7, "day_pct": 0.012, "pace": 1.1426, "tp": 0.2442, "vs_vwap": -0.0001, "dollar_w": 4559.4, "dshare": -0.0003, "state": "FADING", "note": "pace 0.2x vs peak 5.4x \u00b7 -0.8% off HOD \u00b7 chart still +1% \u2014 crowd buying a cooled tape", "peak_tp": 5.419, "surge": 0.1459}, {"ticker": "NTGR", "last": 25.55, "day_pct": 0.0187, "pace": 0.3602, "tp": 0.2667, "vs_vwap": 0.0269, "dollar_w": 4522.35, "dshare": 0.0006, "state": "QUIET", "note": "", "peak_tp": 1.3121, "surge": 0.1604}, {"ticker": "VNM", "last": 16.565, "day_pct": -0.0081, "pace": 0.5965, "tp": 0.3457, "vs_vwap": 0.0005, "dollar_w": 3313.0, "dshare": -0.0002, "state": "COOLING", "note": "pace 0.3x off peak 5.3x", "peak_tp": 5.2726, "surge": 0.2025}, {"ticker": "MSBI", "last": 32.14, "day_pct": 0.0368, "pace": 0.6926, "tp": 0.3208, "vs_vwap": 0.012, "dollar_w": 3214.0, "dshare": -0.0011, "state": "FADING", "note": "pace 0.3x vs peak 2.6x \u00b7 -0.4% off HOD \u00b7 chart still +4% \u2014 crowd buying a cooled tape", "peak_tp": 2.6424, "surge": 0.1964}, {"ticker": "BDN", "last": 3.175, "day_pct": 0.0342, "pace": 0.637, "tp": 0.2705, "vs_vwap": 0.0102, "dollar_w": 2660.65, "dshare": 0.0002, "state": "FADING", "note": "pace 0.3x vs peak 6.4x \u00b7 -0.3% off HOD \u00b7 chart still +3% \u2014 crowd buying a cooled tape", "peak_tp": 6.3928, "surge": 0.1652}, {"ticker": "ADVB", "last": 18.43, "day_pct": 0.099, "pace": 1.1429, "tp": 0.2361, "vs_vwap": -0.0541, "dollar_w": 1916.72, "dshare": -0.0005, "state": "LEAVING", "note": "pace 0.2x off peak 4.0x \u00b7 VWAP lost (was +4.8% above)", "peak_tp": 3.9814, "surge": 0.1532}, {"ticker": "CGBD", "last": 10.04, "day_pct": 0.002, "pace": 0.2992, "tp": 0.0735, "vs_vwap": 0.0, "dollar_w": 1004.0, "dshare": -0.001, "state": "QUIET", "note": "", "peak_tp": 1.3822, "surge": 0.0435}, {"ticker": "AFK", "last": 25.47, "day_pct": 0.0051, "pace": 19.7022, "tp": 0.0, "vs_vwap": 0.0038, "dollar_w": 0.0, "dshare": 0.0, "state": "FADING", "note": "pace 0.0x vs peak 143.7x \u00b7 +0.0% off HOD \u00b7 chart still +1% \u2014 crowd buying a cooled tape", "peak_tp": 143.7047, "surge": 0.0}, {"ticker": "AVLC", "last": 88.92, "day_pct": 0.0012, "pace": 0.4603, "tp": 0.0, "vs_vwap": 0.0, "dollar_w": 0.0, "dshare": 0.0, "state": "FADING", "note": "pace 0.0x vs peak 6.2x \u00b7 +0.0% off HOD \u00b7 chart still +0% \u2014 crowd buying a cooled tape", "peak_tp": 6.2215, "surge": 0.0}, {"ticker": "BTCI", "last": 28.4, "day_pct": -0.0068, "pace": 2.0591, "tp": 0.0, "vs_vwap": 0.0034, "dollar_w": 0.0, "dshare": 0.0, "state": "QUIET", "note": "", "peak_tp": 1.5781, "surge": 0.0}, {"ticker": "AVIV", "last": 79.355, "day_pct": 0.0094, "pace": 0.1362, "tp": 0.0, "vs_vwap": 0.0011, "dollar_w": 0.0, "dshare": 0.0, "state": "QUIET", "note": "", "peak_tp": 1.1181, "surge": 0.0}, {"ticker": "AWP", "last": 12.22, "day_pct": 0.0116, "pace": 3.0195, "tp": 0.0, "vs_vwap": -0.0026, "dollar_w": 0.0, "dshare": 0.0, "state": "FADING", "note": "pace 0.0x vs peak 4.8x \u00b7 -0.5% off HOD \u00b7 chart still +1% \u2014 crowd buying a cooled tape", "peak_tp": 4.7574, "surge": 0.0}, {"ticker": "BILZ", "last": 100.875, "day_pct": 0.0002, "pace": 2.3767, "tp": 0.0, "vs_vwap": 0.0, "dollar_w": 0.0, "dshare": 0.0, "state": "FADING", "note": "pace 0.0x vs peak 35.8x \u00b7 +0.0% off HOD \u00b7 chart still +0% \u2014 crowd buying a cooled tape", "peak_tp": 35.7682, "surge": 0.0}, {"ticker": "CBRZ", "last": 15.36, "day_pct": 0.1463, "pace": 9.6514, "tp": 0.0, "vs_vwap": -0.0133, "dollar_w": 0.0, "dshare": -0.0018, "state": "FADING", "note": "pace 0.0x vs peak 25.0x \u00b7 -6.9% off HOD \u00b7 chart still +15% \u2014 crowd buying a cooled tape", "peak_tp": 25.0474, "surge": 0.0}, {"ticker": "LEMB", "last": 42.155, "day_pct": 0.0049, "pace": 2.9389, "tp": 0.0, "vs_vwap": 0.0014, "dollar_w": 0.0, "dshare": 0.0, "state": "FADING", "note": "pace 0.0x vs peak 11.8x \u00b7 -0.0% off HOD \u00b7 chart still +0% \u2014 crowd buying a cooled tape", "peak_tp": 11.8411, "surge": 0.0}, {"ticker": "ALOT", "last": 28.75, "day_pct": 0.0017, "pace": 0.4673, "tp": 0.0, "vs_vwap": -0.0002, "dollar_w": 0.0, "dshare": 0.0, "state": "FADING", "note": "pace 0.0x vs peak 4.6x \u00b7 -0.1% off HOD \u00b7 chart still +0% \u2014 crowd buying a cooled tape", "peak_tp": 4.6169, "surge": 0.0}, {"ticker": "ATLO", "last": 30.34, "day_pct": 0.0195, "pace": 0.2303, "tp": 0.0, "vs_vwap": 0.0026, "dollar_w": 0.0, "dshare": 0.0, "state": "QUIET", "note": "", "peak_tp": 1.1934, "surge": 0.0}, {"ticker": "BFLX", "last": 25.385, "day_pct": 0.0067, "pace": 0.757, "tp": 0.0, "vs_vwap": 0.0003, "dollar_w": 0.0, "dshare": 0.0, "state": "FADING", "note": "pace 0.0x vs peak 7.0x \u00b7 -0.1% off HOD \u00b7 chart still +1% \u2014 crowd buying a cooled tape", "peak_tp": 6.994, "surge": 0.0}, {"ticker": "BSCR", "last": 19.575, "day_pct": 0.0, "pace": 2.7171, "tp": 0.0, "vs_vwap": 0.0, "dollar_w": 0.0, "dshare": 0.0, "state": "COOLING", "note": "pace 0.0x off peak 9.1x", "peak_tp": 9.1278, "surge": 0.0}, {"ticker": "ITM", "last": 46.0, "day_pct": 0.0033, "pace": 0.2084, "tp": 0.0, "vs_vwap": 0.0012, "dollar_w": 0.0, "dshare": 0.0, "state": "FADING", "note": "pace 0.0x vs peak 7.1x \u00b7 +0.0% off HOD \u00b7 chart still +0% \u2014 crowd buying a cooled tape", "peak_tp": 7.139, "surge": 0.0}, {"ticker": "ACIO", "last": 45.95, "day_pct": 0.0064, "pace": 0.7285, "tp": 0.0, "vs_vwap": 0.0008, "dollar_w": 0.0, "dshare": -0.0005, "state": "FADING", "note": "pace 0.0x vs peak 8.8x \u00b7 +0.0% off HOD \u00b7 chart still +1% \u2014 crowd buying a cooled tape", "peak_tp": 8.7766, "surge": 0.0}, {"ticker": "CHMG", "last": 79.46, "day_pct": 0.0682, "pace": 1.3532, "tp": 0.0, "vs_vwap": 0.0038, "dollar_w": 0.0, "dshare": 0.0, "state": "QUIET", "note": "", "peak_tp": 1.4677, "surge": 0.0}, {"ticker": "HYLS", "last": 40.44, "day_pct": 0.0011, "pace": 1.1063, "tp": 0.0, "vs_vwap": 0.0006, "dollar_w": 0.0, "dshare": -0.0027, "state": "FADING", "note": "pace 0.0x vs peak 10.6x \u00b7 +0.0% off HOD \u00b7 chart still +0% \u2014 crowd buying a cooled tape", "peak_tp": 10.6199, "surge": 0.0}, {"ticker": "BELFA", "last": 237.07, "day_pct": -0.019, "pace": 0.694, "tp": 0.0, "vs_vwap": 0.0117, "dollar_w": 0.0, "dshare": 0.0, "state": "COOLING", "note": "pace 0.0x off peak 3.2x", "peak_tp": 3.1898, "surge": 0.0}, {"ticker": "ADX", "last": 26.01, "day_pct": 0.0035, "pace": 0.7679, "tp": 0.0, "vs_vwap": -0.0008, "dollar_w": 0.0, "dshare": 0.0, "state": "FADING", "note": "pace 0.0x vs peak 6.0x \u00b7 -0.2% off HOD \u00b7 chart still +0% \u2014 crowd buying a cooled tape", "peak_tp": 5.9692, "surge": 0.0}, {"ticker": "BCAL", "last": 21.03, "day_pct": 0.0137, "pace": 0.2643, "tp": 0.0, "vs_vwap": 0.0023, "dollar_w": 0.0, "dshare": 0.0, "state": "QUIET", "note": "", "peak_tp": 1.4726, "surge": 0.0}, {"ticker": "HTH", "last": 40.14, "day_pct": 0.0611, "pace": 0.5418, "tp": 0.0, "vs_vwap": 0.0068, "dollar_w": 0.0, "dshare": -0.0008, "state": "FADING", "note": "pace 0.0x vs peak 2.0x \u00b7 -0.3% off HOD \u00b7 chart still +6% \u2014 crowd buying a cooled tape", "peak_tp": 2.0415, "surge": 0.0}, {"ticker": "ACOG", "last": 7.915, "day_pct": -0.0288, "pace": 0.6551, "tp": 0.0, "vs_vwap": -0.026, "dollar_w": 0.0, "dshare": 0.0, "state": "COOLING", "note": "pace 0.0x off peak 4.7x", "peak_tp": 4.7045, "surge": 0.0}, {"ticker": "ASR", "last": 266.2, "day_pct": -0.0132, "pace": 1.8841, "tp": 0.0, "vs_vwap": 0.0109, "dollar_w": 0.0, "dshare": 0.0, "state": "COOLING", "note": "pace 0.0x off peak 2.1x", "peak_tp": 2.113, "surge": 0.0}, {"ticker": "BGSI", "last": 102.7, "day_pct": 0.0136, "pace": 0.1352, "tp": 0.0, "vs_vwap": 0.0, "dollar_w": 0.0, "dshare": 0.0, "state": "FADING", "note": "pace 0.0x vs peak 2.2x \u00b7 +0.0% off HOD \u00b7 chart still +1% \u2014 crowd buying a cooled tape", "peak_tp": 2.2179, "surge": 0.0}, {"ticker": "FSBC", "last": 47.62, "day_pct": 0.0075, "pace": 0.2936, "tp": 0.0, "vs_vwap": 0.0084, "dollar_w": 0.0, "dshare": 0.0, "state": "QUIET", "note": "", "peak_tp": 1.6521, "surge": 0.0}, {"ticker": "CJMB", "last": 2.3, "day_pct": -0.0086, "pace": 7.0343, "tp": 0.0, "vs_vwap": -0.191, "dollar_w": 0.0, "dshare": -0.0001, "state": "LEAVING", "note": "pace 0.0x off peak 27.1x \u00b7 VWAP lost (was +15.8% above)", "peak_tp": 27.1435, "surge": 0.0}, {"ticker": "BBSI", "last": 39.635, "day_pct": -0.0034, "pace": 0.0748, "tp": 0.0, "vs_vwap": -0.0012, "dollar_w": 0.0, "dshare": 0.0, "state": "QUIET", "note": "", "peak_tp": 0.6093, "surge": 0.0}, {"ticker": "CHT", "last": 42.74, "day_pct": 0.0081, "pace": 0.1674, "tp": 0.0, "vs_vwap": -0.0008, "dollar_w": 0.0, "dshare": -0.0009, "state": "QUIET", "note": "", "peak_tp": 1.5438, "surge": 0.0}, {"ticker": "HYLB", "last": 36.18, "day_pct": 0.001, "pace": 2.2309, "tp": 0.0, "vs_vwap": 0.0006, "dollar_w": 0.0, "dshare": 0.0, "state": "FADING", "note": "pace 0.0x vs peak 13.6x \u00b7 +0.0% off HOD \u00b7 chart still +0% \u2014 crowd buying a cooled tape", "peak_tp": 13.5735, "surge": 0.0}, {"ticker": "BAB", "last": 26.39, "day_pct": 0.0027, "pace": 0.0835, "tp": 0.0, "vs_vwap": 0.0004, "dollar_w": 0.0, "dshare": 0.0, "state": "QUIET", "note": "", "peak_tp": 0.5527, "surge": 0.0}, {"ticker": "BEDY", "last": 29.27, "day_pct": 0.01, "pace": 0.0658, "tp": 0.0, "vs_vwap": 0.0, "dollar_w": 0.0, "dshare": 0.0, "state": "QUIET", "note": "", "peak_tp": 0.7503, "surge": 0.0}, {"ticker": "ACNB", "last": 62.7, "day_pct": -0.0025, "pace": 2.6861, "tp": 0.0, "vs_vwap": 0.0018, "dollar_w": 0.0, "dshare": 0.0, "state": "COOLING", "note": "pace 0.0x off peak 8.4x", "peak_tp": 8.4267, "surge": 0.0}, {"ticker": "CCIX", "last": 10.875, "day_pct": 0.0005, "pace": 6.2115, "tp": 0.0, "vs_vwap": 0.0005, "dollar_w": 0.0, "dshare": 0.0, "state": "FADING", "note": "pace 0.0x vs peak 23.8x \u00b7 +0.0% off HOD \u00b7 chart still +0% \u2014 crowd buying a cooled tape", "peak_tp": 23.7536, "surge": 0.0}, {"ticker": "NEA", "last": 11.265, "day_pct": 0.0036, "pace": 0.654, "tp": 0.0, "vs_vwap": 0.0007, "dollar_w": 0.0, "dshare": 0.0, "state": "FADING", "note": "pace 0.0x vs peak 2.0x \u00b7 -0.1% off HOD \u00b7 chart still +0% \u2014 crowd buying a cooled tape", "peak_tp": 2.0452, "surge": 0.0}, {"ticker": "BOW", "last": 30.67, "day_pct": 0.0386, "pace": 0.1621, "tp": 0.0, "vs_vwap": 0.0, "dollar_w": 0.0, "dshare": 0.0, "state": "FADING", "note": "pace 0.0x vs peak 2.1x \u00b7 +0.0% off HOD \u00b7 chart still +4% \u2014 crowd buying a cooled tape", "peak_tp": 2.1482, "surge": 0.0}, {"ticker": "BUFZ", "last": 27.985, "day_pct": 0.0045, "pace": 0.1965, "tp": 0.0, "vs_vwap": 0.0004, "dollar_w": 0.0, "dshare": 0.0, "state": "FADING", "note": "pace 0.0x vs peak 2.8x \u00b7 +0.0% off HOD \u00b7 chart still +0% \u2014 crowd buying a cooled tape", "peak_tp": 2.8088, "surge": 0.0}, {"ticker": "CIB", "last": 87.83, "day_pct": 0.0144, "pace": 1.7847, "tp": 0.0, "vs_vwap": 0.0032, "dollar_w": 0.0, "dshare": 0.0, "state": "FADING", "note": "pace 0.0x vs peak 15.7x \u00b7 +0.0% off HOD \u00b7 chart still +1% \u2014 crowd buying a cooled tape", "peak_tp": 15.6666, "surge": 0.0}], "rot_in": [{"ticker": "CHIQ", "surge": 20.68}, {"ticker": "CDXS", "surge": 5.77}, {"ticker": "CCB", "surge": 3.41}, {"ticker": "BSJU", "surge": 1.74}], "rot_out": [{"ticker": "AFK", "frac": 0.0}, {"ticker": "AVLC", "frac": 0.0}, {"ticker": "AWP", "frac": 0.0}, {"ticker": "BILZ", "frac": 0.0}]}